crestron_swamp_controller-1.0.0.dist-info/licenses/LICENSE
swamp/__init__.py
swamp/__main__.py
swamp/core/__init__.py
swamp/core/config_manager.py
swamp/core/controller.py
swamp/core/state_manager.py
swamp/models/__init__.py
swamp/models/commands.py
swamp/models/config.py
swamp/models/state.py
swamp/network/__init__.py
swamp/network/tcp_server.py
swamp/protocol/__init__.py
swamp/protocol/base.py
swamp/protocol/swamp_protocol.py
swamp/shell/__init__.py
swamp/shell/commands.py
swamp/shell/parser.py
swamp/shell/repl.py
crestron_swamp_controller-1.0.0.dist-info/METADATA
crestron_swamp_controller-1.0.0.dist-info/WHEEL
crestron_swamp_controller-1.0.0.dist-info/entry_points.txt
crestron_swamp_controller-1.0.0.dist-info/top_level.txt
crestron_swamp_controller-1.0.0.dist-info/RECORD
