Metadata-Version: 2.4
Name: crestron-swamp-controller
Version: 1.0.0
Summary: Interactive controller for Crestron SWAMP media amplifier systems
Author-email: jaroy <noreply@github.com>
License-Expression: MIT
Project-URL: Homepage, https://github.com/jaroy/swamp-controller
Project-URL: Documentation, https://github.com/jaroy/swamp-controller#readme
Project-URL: Repository, https://github.com/jaroy/swamp-controller
Project-URL: Issues, https://github.com/jaroy/swamp-controller/issues
Keywords: crestron,swamp,home-assistant,audio,multi-zone
Classifier: Development Status :: 4 - Beta
Classifier: Intended Audience :: End Users/Desktop
Classifier: Programming Language :: Python :: 3
Classifier: Programming Language :: Python :: 3.12
Classifier: Topic :: Home Automation
Requires-Python: >=3.12
License-File: LICENSE
Requires-Dist: pyyaml>=6.0.1
Requires-Dist: prompt-toolkit>=3.0.43
Provides-Extra: dev
Requires-Dist: pytest>=7.4.3; extra == "dev"
Requires-Dist: pytest-asyncio>=0.23.0; extra == "dev"
Dynamic: license-file
